model_signing/__init__.py
model_signing/__main__.py
model_signing/_cli.py
model_signing/hashing.py
model_signing/manifest.py
model_signing/py.typed
model_signing/signing.py
model_signing/verifying.py
model_signing/_hashing/__init__.py
model_signing/_hashing/hashing.py
model_signing/_hashing/io.py
model_signing/_hashing/memory.py
model_signing/_serialization/__init__.py
model_signing/_serialization/file.py
model_signing/_serialization/file_shard.py
model_signing/_serialization/serialization.py
model_signing/_signing/__init__.py
model_signing/_signing/pkcs11uri.py
model_signing/_signing/sign_certificate.py
model_signing/_signing/sign_ec_key.py
model_signing/_signing/sign_pkcs11.py
model_signing/_signing/sign_sigstore.py
model_signing/_signing/sign_sigstore_pb.py
model_signing/_signing/signing.py
model_signing-1.1.1.dist-info/METADATA
model_signing-1.1.1.dist-info/WHEEL
model_signing-1.1.1.dist-info/entry_points.txt
model_signing-1.1.1.dist-info/licenses/LICENSE
model_signing-1.1.1.dist-info/RECORD
