Metadata-Version: 2.4
Name: model-signing
Version: 1.1.1
Summary: A tool for signing and verifying ML models
Project-URL: Homepage, https://pypi.org/project/model-signing/
Project-URL: Changelog, https://github.com/sigstore/model-transparency/blob/main/CHANGELOG.md
Project-URL: Documentation, https://sigstore.github.io/model-transparency/model_signing.html
Project-URL: Source, https://github.com/sigstore/model-transparency
Project-URL: Issues, https://github.com/sigstore/model-transparency/issues
Project-URL: PyPI, https://pypi.org/project/model-signing/
Author-email: Sigstore Authors <sigstore-dev@googlegroups.com>
License-Expression: Apache-2.0
License-File: LICENSE
Keywords: AI security,AI supply chain security,ML security,ML supply chain security,artificial intelligence,machine learning,model signing
Classifier: Development Status :: 3 - Alpha
Classifier: Intended Audience :: Developers
Classifier: Programming Language :: Python :: 3
Classifier: Programming Language :: Python :: 3 :: Only
Classifier: Programming Language :: Python :: 3.9
Classifier: Programming Language :: Python :: 3.10
Classifier: Programming Language :: Python :: 3.11
Classifier: Programming Language :: Python :: 3.12
Classifier: Programming Language :: Python :: 3.13
Classifier: Topic :: Scientific/Engineering :: Artificial Intelligence
Classifier: Topic :: Security
Classifier: Topic :: Security :: Cryptography
Classifier: Typing :: Typed
Requires-Python: >=3.9
Requires-Dist: asn1crypto
Requires-Dist: blake3
Requires-Dist: click
Requires-Dist: cryptography
Requires-Dist: in-toto-attestation
Requires-Dist: sigstore-models>=0.0.5
Requires-Dist: sigstore>=4.0
Requires-Dist: typing-extensions
Provides-Extra: otel
Requires-Dist: opentelemetry-api; extra == 'otel'
Requires-Dist: opentelemetry-distro; extra == 'otel'
Requires-Dist: opentelemetry-exporter-otlp; extra == 'otel'
Requires-Dist: opentelemetry-instrumentation; extra == 'otel'
Requires-Dist: opentelemetry-instrumentation-urllib3; extra == 'otel'
Requires-Dist: opentelemetry-sdk; extra == 'otel'
Provides-Extra: pkcs11
Requires-Dist: pykcs11; extra == 'pkcs11'
